utils/__init__.py
utils/alist/__init__.py
utils/alist/client.py
utils/alist/credential.py
utils/alist/response.py
utils/cli/__init__.py
utils/cli/alist/__init__.py
utils/cli/alist/main.py
utils/cli/alist/upload.py
utils/cli/github/__init__.py
utils/cli/github/clone.py
utils/cli/github/main.py
utils/cli/main.py
utils/typer/__init__.py
utils/typer/command.py
utils_cli-0.1.0.dist-info/METADATA
utils_cli-0.1.0.dist-info/WHEEL
utils_cli-0.1.0.dist-info/entry_points.txt
utils_cli-0.1.0.dist-info/RECORD
